revenium_middleware_litellm-0.3.0.dist-info/licenses/LICENSE
revenium_middleware_litellm_client/__init__.py
revenium_middleware_litellm_client/context.py
revenium_middleware_litellm_client/decorators.py
revenium_middleware_litellm_client/hooks.py
revenium_middleware_litellm_client/middleware.py
revenium_middleware_litellm_client/trace_fields.py
revenium_middleware_litellm_client/validation.py
revenium_middleware_litellm_client/integrations/__init__.py
revenium_middleware_litellm_client/integrations/crewai.py
revenium_middleware_litellm_proxy/__init__.py
revenium_middleware_litellm_proxy/middleware.py
revenium_middleware_litellm-0.3.0.dist-info/METADATA
revenium_middleware_litellm-0.3.0.dist-info/WHEEL
revenium_middleware_litellm-0.3.0.dist-info/top_level.txt
revenium_middleware_litellm-0.3.0.dist-info/RECORD
