Metadata-Version: 2.4
Name: revenium-middleware-litellm
Version: 0.3.0
Summary: A Python library that meters LiteLLM usage to Revenium with context-based metadata injection and framework integrations.
Author-email: Revenium <info@revenium.io>
License-Expression: MIT
Project-URL: Homepage, https://github.com/revenium/revenium-middleware-litellm-proxy-python
Project-URL: Bug Tracker, https://github.com/revenium/revenium-middleware-litellm-proxy-python/issues
Project-URL: Documentation, https://docs.revenium.io
Project-URL: Repository, https://github.com/revenium/revenium-middleware-litellm-proxy-python
Keywords: litellm,middleware,logging,token-usage,metering,revenium
Classifier: Development Status :: 4 - Beta
Classifier: Programming Language :: Python :: 3
Classifier: Programming Language :: Python :: 3.8
Classifier: Programming Language :: Python :: 3.9
Classifier: Programming Language :: Python :: 3.10
Classifier: Programming Language :: Python :: 3.11
Classifier: Programming Language :: Python :: 3.12
Classifier: Operating System :: OS Independent
Classifier: Intended Audience :: Developers
Classifier: Topic :: Software Development :: Libraries :: Python Modules
Requires-Python: >=3.8
License-File: LICENSE
Requires-Dist: wrapt
Requires-Dist: revenium_middleware>=0.4.0
Requires-Dist: litellm
Provides-Extra: test
Requires-Dist: pytest>=8.0.0; extra == "test"
Requires-Dist: pytest-asyncio>=1.2.0; extra == "test"
Requires-Dist: python-dotenv>=1.0.0; extra == "test"
Provides-Extra: dev
Requires-Dist: pytest>=8.0.0; extra == "dev"
Requires-Dist: pytest-asyncio>=1.2.0; extra == "dev"
Requires-Dist: python-dotenv>=1.0.0; extra == "dev"
Requires-Dist: black>=23.0.0; extra == "dev"
Requires-Dist: isort>=5.12.0; extra == "dev"
Requires-Dist: mypy>=1.0.0; extra == "dev"
Provides-Extra: validation
Requires-Dist: pydantic>=2.0.0; extra == "validation"
Provides-Extra: crewai
Requires-Dist: crewai>=0.1.0; extra == "crewai"
Provides-Extra: litellm-proxy
Requires-Dist: litellm[proxy]; extra == "litellm-proxy"
Requires-Dist: revenium_middleware>=0.4.0; extra == "litellm-proxy"
Provides-Extra: litellm-client
Requires-Dist: litellm; extra == "litellm-client"
Requires-Dist: wrapt; extra == "litellm-client"
Requires-Dist: revenium_middleware>=0.4.0; extra == "litellm-client"
Provides-Extra: litellm-all
Requires-Dist: litellm[proxy]; extra == "litellm-all"
Requires-Dist: litellm; extra == "litellm-all"
Requires-Dist: wrapt; extra == "litellm-all"
Requires-Dist: revenium_middleware>=0.4.0; extra == "litellm-all"
Requires-Dist: pydantic>=2.0.0; extra == "litellm-all"
Requires-Dist: crewai>=0.1.0; extra == "litellm-all"
Dynamic: license-file
